bsolver/__init__.py
bsolver/arbre.py
bsolver-0.1.1.dist-info/METADATA
bsolver-0.1.1.dist-info/WHEEL
bsolver-0.1.1.dist-info/top_level.txt
bsolver-0.1.1.dist-info/RECORD
