Metadata-Version: 2.4
Name: bsolver
Version: 0.1.1
Summary: Un solveur d'expressions booléenes
Author-email: "Jimmy C. (Jimw)" <jimmy.c@jimw.fr>
License-Expression: MIT
Classifier: Programming Language :: Python :: 3
Classifier: Operating System :: OS Independent
Classifier: Intended Audience :: Developers
Classifier: Topic :: Software Development :: Libraries
Classifier: Topic :: Scientific/Engineering :: Mathematics
Requires-Python: >=3.8
